[{"pk": 1, "model": "ingreso.rubros", "fields": {"nombre": "Aguacate", "unidad": "Cien"}}, {"pk": 2, "model": "ingreso.rubros", "fields": {"nombre": "Ajonjol\u00ed", "unidad": "Quintales"}}, {"pk": 3, "model": "ingreso.rubros", "fields": {"nombre": "Arroz", "unidad": "Quintales"}}, {"pk": 4, "model": "ingreso.rubros", "fields": {"nombre": "Aves", "unidad": "Unidad"}}, {"pk": 5, "model": "ingreso.rubros", "fields": {"nombre": "Cacao", "unidad": "Quintales"}}, {"pk": 6, "model": "ingreso.rubros", "fields": {"nombre": "caf\u00e9", "unidad": "Quintales"}}, {"pk": 7, "model": "ingreso.rubros", "fields": {"nombre": "Cebolla", "unidad": "Libras"}}, {"pk": 8, "model": "ingreso.rubros", "fields": {"nombre": "Chiltoma", "unidad": "Libras"}}, {"pk": 9, "model": "ingreso.rubros", "fields": {"nombre": "Cuajada", "unidad": "Libras"}}, {"pk": 10, "model": "ingreso.rubros", "fields": {"nombre": "Frijol", "unidad": "Quintales"}}, {"pk": 11, "model": "ingreso.rubros", "fields": {"nombre": "Guineo", "unidad": "Cabeza"}}, {"pk": 12, "model": "ingreso.rubros", "fields": {"nombre": "Huevos", "unidad": "Docena"}}, {"pk": 13, "model": "ingreso.rubros", "fields": {"nombre": "Jocote", "unidad": "Lata"}}, {"pk": 14, "model": "ingreso.rubros", "fields": {"nombre": "Leche", "unidad": "Litros"}}, {"pk": 15, "model": "ingreso.rubros", "fields": {"nombre": "Lim\u00f3n", "unidad": "Cien"}}, {"pk": 16, "model": "ingreso.rubros", "fields": {"nombre": "Ma\u00edz", "unidad": "Quintales"}}, {"pk": 17, "model": "ingreso.rubros", "fields": {"nombre": "Malanga", "unidad": "Quintales"}}, {"pk": 18, "model": "ingreso.rubros", "fields": {"nombre": "Mango", "unidad": "Cien"}}, {"pk": 19, "model": "ingreso.rubros", "fields": {"nombre": "Mill\u00f3n", "unidad": "Quintales"}}, {"pk": 20, "model": "ingreso.rubros", "fields": {"nombre": "Naranja", "unidad": "Cien"}}, {"pk": 21, "model": "ingreso.rubros", "fields": {"nombre": "Pepino", "unidad": "Docena"}}, {"pk": 22, "model": "ingreso.rubros", "fields": {"nombre": "Pl\u00e1tano", "unidad": "Cabeza"}}, {"pk": 23, "model": "ingreso.rubros", "fields": {"nombre": "Quequisque", "unidad": "Quintales"}}, {"pk": 24, "model": "ingreso.rubros", "fields": {"nombre": "Queso", "unidad": "Libras"}}, {"pk": 25, "model": "ingreso.rubros", "fields": {"nombre": "Sorgo", "unidad": "Quintales"}}, {"pk": 26, "model": "ingreso.rubros", "fields": {"nombre": "Ternero de desarrollo", "unidad": "Cabeza"}}, {"pk": 27, "model": "ingreso.rubros", "fields": {"nombre": "Tomate", "unidad": "Libras"}}, {"pk": 28, "model": "ingreso.rubros", "fields": {"nombre": "Vaca", "unidad": "Cabeza"}}, {"pk": 29, "model": "ingreso.rubros", "fields": {"nombre": "Yuca", "unidad": "Quintales"}}]
